edicat/__init__.py
edicat/__main__.py
edicat/edi.py
edicat-2024.8.2.dist-info/METADATA
edicat-2024.8.2.dist-info/WHEEL
edicat-2024.8.2.dist-info/entry_points.txt
edicat-2024.8.2.dist-info/licenses/LICENSE
edicat-2024.8.2.dist-info/RECORD
