Metadata-Version: 2.3
Name: edicat
Version: 2024.8.2
Summary: Print and concatenate EDI files
Project-URL: Homepage, https://github.com/notpeter/edicat
Project-URL: Repository, https://github.com/notpeter/edicat.git
Author-email: Peter Tripp <peter.tripp@gmail.com>
License-Expression: MIT
License-File: LICENSE
Keywords: ansix12,edi,edicat,edifact
Classifier: Development Status :: 4 - Beta
Classifier: Environment :: Console
Classifier: Intended Audience :: Developers
Classifier: License :: OSI Approved :: MIT License
Classifier: Operating System :: OS Independent
Classifier: Programming Language :: Python
Classifier: Programming Language :: Python :: 3
Classifier: Programming Language :: Python :: 3 :: Only
Classifier: Programming Language :: Python :: 3.7
Classifier: Programming Language :: Python :: 3.8
Classifier: Programming Language :: Python :: 3.9
Classifier: Programming Language :: Python :: 3.10
Classifier: Topic :: Software Development :: Libraries :: Python Modules
Classifier: Topic :: Text Processing
Classifier: Topic :: Utilities
Requires-Python: >=3.7
Provides-Extra: dev
Requires-Dist: black; extra == 'dev'
Requires-Dist: flake8; extra == 'dev'
